{
    "type": "minecraft:crafting_shaped",
    "category": "misc",
    "pattern": [
      "  N",
      " S ",
      "S  "
    ],
    "key": {
      "S": "minecraft:stick",
      "N": "minecraft:netherite_ingot"
    },
    "result": {
      "id": "minecraft:clock",
      "components": {
        "minecraft:custom_name": "Netherite Wand",
        "minecraft:rarity": "common",
        "minecraft:custom_data": {
          "type": "wand",
          "enchanted": false,
          "tier": 7,
          "model": "magick_reborn:netherite_wand"
        },
        "repairable": {
          "items": [
            "lapis_lazuli"
          ]
        },
        "repair_cost": 2,
        "minecraft:item_model": "magick_reborn:netherite_wand",
        "max_stack_size": 1,
        "max_damage": 1000,
        "damage": 0
      },
      "count": 1
    },
    "show_notification": true
  }